walnut_cli/__init__.py
walnut_cli/aux/downloadthis.zip
walnut_cli/aux/walnut-6.2.jar
walnut_cli/aux/walnut.xml
walnut_cli-0.8.dist-info/METADATA
walnut_cli-0.8.dist-info/WHEEL
walnut_cli-0.8.dist-info/entry_points.txt
walnut_cli-0.8.dist-info/RECORD
